.flake8
.gitignore
.travis.yml
LICENSE
README.md
README.pypi.rst
client_dev.py
dev-requirements.txt
dev_glue.py
requirements.txt
setup.py
docs/Makefile
docs/api.rst
docs/conf.py
docs/index.rst
docs/status.rst
docs/_static/logo_ga.png
ga4gh/__init__.py
ga4gh/client/__init__.py
ga4gh/client/_version.py
ga4gh/client/cli.py
ga4gh/client/client.py
ga4gh/client/exceptions.py
ga4gh/client/protocol.py
ga4gh_client.egg-info/PKG-INFO
ga4gh_client.egg-info/SOURCES.txt
ga4gh_client.egg-info/dependency_links.txt
ga4gh_client.egg-info/entry_points.txt
ga4gh_client.egg-info/namespace_packages.txt
ga4gh_client.egg-info/requires.txt
ga4gh_client.egg-info/top_level.txt
ga4gh_client.egg-info/zip-safe
tests/__init__.py
tests/unit/__init__.py
tests/unit/test_cli.py
tests/unit/test_client.py
tools/travis-install-protoc.sh